Jpc/__init__.py
Jpc/module.py
Jynpc-0.3.dist-info/LICENSE
Jynpc-0.3.dist-info/METADATA
Jynpc-0.3.dist-info/WHEEL
Jynpc-0.3.dist-info/top_level.txt
Jynpc-0.3.dist-info/RECORD
